qeng/__init__.py
qeng/api.py
qeng/version.py
qeng/game/__init__.py
qeng/game/bonus.py
qeng/game/game.py
qeng/game/game_metadata.py
qeng/game/hint.py
qeng/game/level.py
qeng/game/level_metadata.py
qeng/game/level_sector.py
qeng/game/passing_sequence.py
qeng_admin_api-1.5.1.dist-info/METADATA
qeng_admin_api-1.5.1.dist-info/WHEEL
qeng_admin_api-1.5.1.dist-info/top_level.txt
qeng_admin_api-1.5.1.dist-info/RECORD
