Metadata-Version: 2.1
Name: qeng-admin-api
Version: 1.5.1
Summary: Administrative API for the QEng quest engine
Home-page: UNKNOWN
Author: phaust94
Author-email: phaust94@gmail.com
License: UNKNOWN
Project-URL: Homepage, https://github.com/Phaust94/qeng_admin_api
Platform: UNKNOWN
